{
  "main": {
    "id": "b8692181d1fda20f",
    "type": "split",
    "children": [
      {
        "id": "39b9b6ae93045c1b",
        "type": "tabs",
        "children": [
          {
            "id": "90d6e29d539645c9",
            "type": "leaf",
            "state": {
              "type": "markdown",
              "state": {
                "file": "TODO LIST.md",
                "mode": "source",
                "source": false
              },
              "icon": "lucide-file",
              "title": "TODO LIST"
            }
          },
          {
            "id": "00c5ae393333d3ef",
            "type": "leaf",
            "state": {
              "type": "markdown",
              "state": {
                "file": "git.md",
                "mode": "source",
                "source": false
              },
              "icon": "lucide-file",
              "title": "git"
            }
          },
          {
            "id": "3f87369e9aab7f78",
            "type": "leaf",
            "state": {
              "type": "markdown",
              "state": {
                "file": "journal/2025/07/2025-07-12.md",
                "mode": "source",
                "source": false
              },
              "icon": "lucide-file",
              "title": "2025-07-12"
            }
          },
          {
            "id": "f86ad2193ac16469",
            "type": "leaf",
            "state": {
              "type": "markdown",
              "state": {
                "file": "journal/2025/07/2025-07-12.md",
                "mode": "source",
                "source": false
              },
              "icon": "lucide-file",
              "title": "2025-07-12"
            }
          },
          {
            "id": "b18aeb260f2001dc",
            "type": "leaf",
            "state": {
              "type": "markdown",
              "state": {
                "file": "Saved Commands.md",
                "mode": "source",
                "source": false
              },
              "icon": "lucide-file",
              "title": "Saved Commands"
            }
          },
          {
            "id": "2fe4d58027d17bce",
            "type": "leaf",
            "state": {
              "type": "markdown",
              "state": {
                "file": "installed stuff in my linux pc.md",
                "mode": "source",
                "source": false
              },
              "icon": "lucide-file",
              "title": "installed stuff in my linux pc"
            }
          },
          {
            "id": "ba6abea5cb6366df",
            "type": "leaf",
            "state": {
              "type": "markdown",
              "state": {
                "file": "CoInAct.md",
                "mode": "source",
                "source": false
              },
              "icon": "lucide-file",
              "title": "CoInAct"
            }
          },
          {
            "id": "ad8202a51b048869",
            "type": "leaf",
            "state": {
              "type": "markdown",
              "state": {
                "file": "TODO LIST.md",
                "mode": "source",
                "source": false
              },
              "icon": "lucide-file",
              "title": "TODO LIST"
            }
          },
          {
            "id": "0dfe25c578f73053",
            "type": "leaf",
            "state": {
              "type": "markdown",
              "state": {
                "file": "Dissertation ALL.md",
                "mode": "source",
                "source": false
              },
              "icon": "lucide-file",
              "title": "Dissertation ALL"
            }
          },
          {
            "id": "f423d08e963fe8d0",
            "type": "leaf",
            "state": {
              "type": "markdown",
              "state": {
                "file": "TODO LIST.md",
                "mode": "source",
                "source": false
              },
              "icon": "lucide-file",
              "title": "TODO LIST"
            }
          },
          {
            "id": "85794618d4f4dd00",
            "type": "leaf",
            "state": {
              "type": "markdown",
              "state": {
                "file": "git.md",
                "mode": "source",
                "source": false
              },
              "icon": "lucide-file",
              "title": "git"
            }
          },
          {
            "id": "4dcd64269cc37674",
            "type": "leaf",
            "state": {
              "type": "markdown",
              "state": {
                "file": "salary.md",
                "mode": "source",
                "source": false
              },
              "icon": "lucide-file",
              "title": "salary"
            }
          }
        ],
        "currentTab": 1
      }
    ],
    "direction": "vertical"
  },
  "left": {
    "id": "a4b0bb3da7b7d997",
    "type": "split",
    "children": [
      {
        "id": "6699acfa9f0a617a",
        "type": "tabs",
        "children": [
          {
            "id": "5d9f8cd535c540a8",
            "type": "leaf",
            "state": {
              "type": "file-explorer",
              "state": {
                "sortOrder": "alphabetical",
                "autoReveal": false
              },
              "icon": "lucide-folder-closed",
              "title": "Files"
            }
          },
          {
            "id": "a2d6c7fa0c799979",
            "type": "leaf",
            "state": {
              "type": "search",
              "state": {
                "query": "MIS",
                "matchingCase": false,
                "explainSearch": false,
                "collapseAll": false,
                "extraContext": false,
                "sortOrder": "alphabetical"
              },
              "icon": "lucide-search",
              "title": "Search"
            }
          },
          {
            "id": "11fa8b4f890421b5",
            "type": "leaf",
            "state": {
              "type": "bookmarks",
              "state": {},
              "icon": "lucide-bookmark",
              "title": "Bookmarks"
            }
          }
        ]
      }
    ],
    "direction": "horizontal",
    "width": 275.5004348754883
  },
  "right": {
    "id": "d1de6df18cf5282b",
    "type": "split",
    "children": [
      {
        "id": "206af973997d4120",
        "type": "tabs",
        "children": [
          {
            "id": "9886368b07d79bed",
            "type": "leaf",
            "state": {
              "type": "backlink",
              "state": {
                "file": "git.md",
                "collapseAll": false,
                "extraContext": false,
                "sortOrder": "alphabetical",
                "showSearch": false,
                "searchQuery": "",
                "backlinkCollapsed": false,
                "unlinkedCollapsed": true
              },
              "icon": "links-coming-in",
              "title": "Backlinks for git"
            }
          },
          {
            "id": "8c8e7ebee5251d67",
            "type": "leaf",
            "state": {
              "type": "outgoing-link",
              "state": {
                "file": "git.md",
                "linksCollapsed": false,
                "unlinkedCollapsed": true
              },
              "icon": "links-going-out",
              "title": "Outgoing links from git"
            }
          },
          {
            "id": "7d6e2c9b1ccdffd1",
            "type": "leaf",
            "state": {
              "type": "tag",
              "state": {
                "sortOrder": "frequency",
                "useHierarchy": true,
                "showSearch": false,
                "searchQuery": ""
              },
              "icon": "lucide-tags",
              "title": "Tags"
            }
          },
          {
            "id": "25d011be83242af2",
            "type": "leaf",
            "state": {
              "type": "outline",
              "state": {
                "file": "git.md",
                "followCursor": false,
                "showSearch": false,
                "searchQuery": ""
              },
              "icon": "lucide-list",
              "title": "Outline of git"
            }
          },
          {
            "id": "e30c8e6f01f0d800",
            "type": "leaf",
            "state": {
              "type": "full-calendar-view",
              "state": {},
              "icon": "calendar-glyph",
              "title": "Calendar"
            }
          },
          {
            "id": "eff2a62fff0231ea",
            "type": "leaf",
            "state": {
              "type": "calendar",
              "state": {},
              "icon": "calendar-with-checkmark",
              "title": "Calendar"
            }
          },
          {
            "id": "2433848e7404478d",
            "type": "leaf",
            "state": {
              "type": "markdown",
              "state": {
                "file": "discrete_ct-finite_if-countable-uncountable.md",
                "mode": "source",
                "source": false
              },
              "icon": "lucide-file",
              "title": "discrete_ct-finite_if-countable-uncountable"
            }
          },
          {
            "id": "e84469d12c5f831f",
            "type": "leaf",
            "state": {
              "type": "git-view",
              "state": {},
              "icon": "git-pull-request",
              "title": "Source Control"
            }
          }
        ],
        "currentTab": 7
      }
    ],
    "direction": "horizontal",
    "width": 581.5
  },
  "left-ribbon": {
    "hiddenItems": {
      "switcher:Open quick switcher": false,
      "graph:Open graph view": false,
      "canvas:Create new canvas": false,
      "daily-notes:Open today's daily note": false,
      "templates:Insert template": false,
      "command-palette:Open command palette": false,
      "periodic-notes:Open today": false,
      "obsidian-full-calendar:Open Full Calendar": false,
      "obsidian-git:Open Git source control": false
    }
  },
  "active": "00c5ae393333d3ef",
  "lastOpenFiles": [
    "journal/2025/07/2025-07-12.md",
    "Purchase list.md",
    "git.md",
    "格言.md",
    "CoinAct - hiring ads.md",
    "installed stuff in my linux pc.md",
    "C3.3 Analaysis strategy.md",
    "made md autocommit.md",
    "Pasted image 20250712201229.png",
    "Pasted image 20250712201146.png",
    "Pasted image 20250712201138.png",
    "Pasted image 20250712201133.png",
    "Pasted image 20250712201128.png",
    "Pasted image 20250712192952.png",
    "Pasted image 20250712192940.png",
    "Pasted image 20250712192933.png",
    "Pasted image 20250712192926.png",
    "Pasted image 20250712184328.png",
    "Saved Commands.md",
    "TODO LIST.md",
    "CoInAct.md",
    "TODO LIST - long term.md",
    "Outline-g.md",
    "Dissertation ALL.md",
    "journal/2025/07/2025-07-10.md",
    "journal/2025/07/2025-07-09.md",
    "discrete_ct-finite_if-countable-uncountable.md",
    "C6, 6 - 6.2.2.md",
    "prepare.md",
    "Model of Intention Selection (MIS).md",
    "UCPH - University of Copenhagen.md",
    "salary.md",
    "Application.md",
    "journal/2025/07/2025-07-08.md",
    "journal/2025/07/2025-07-07.md",
    "journal/2025/06/2025-06-07.md",
    "journal/2025/07",
    "Untitled",
    "conversation/cc-解读1.txt",
    "conversation/cc-解读2.txt",
    "conversation/这儿.txt",
    "conversation/想给你的是璀璨星空 你收到的是暴乱星海.txt",
    "conversation/这儿 (1).txt",
    "conversation/c-焦急他的没有放松.txt",
    "conversation/c-过去的历史.txt",
    "conversation/c-结婚？.txt",
    "Untitled.canvas"
  ]
}